tikit/__init__.py
tikit/client.py
tikit/default_client.py
tikit/hdfs.py
tikit/hive.py
tikit/models.py
tikit/util.py
tikit/display_optimize/__init__.py
tikit/display_optimize/dataset.py
tikit/display_optimize/resource_group.py
tikit/display_optimize/training_model.py
tikit/display_optimize/training_task.py
tikit/tencentcloud/__init__.py
tikit/tencentcloud/common/__init__.py
tikit/tencentcloud/common/abstract_client.py
tikit/tencentcloud/common/abstract_model.py
tikit/tencentcloud/common/common_client.py
tikit/tencentcloud/common/credential.py
tikit/tencentcloud/common/sign.py
tikit/tencentcloud/common/exception/__init__.py
tikit/tencentcloud/common/exception/tencent_cloud_sdk_exception.py
tikit/tencentcloud/common/http/__init__.py
tikit/tencentcloud/common/http/request.py
tikit/tencentcloud/common/profile/__init__.py
tikit/tencentcloud/common/profile/client_profile.py
tikit/tencentcloud/common/profile/http_profile.py
tikit/tencentcloud/tione/__init__.py
tikit/tencentcloud/tione/v20211111/__init__.py
tikit/tencentcloud/tione/v20211111/errorcodes.py
tikit/tencentcloud/tione/v20211111/models.py
tikit/tencentcloud/tione/v20211111/tione_client.py
tikit_en-0.1.220330.dist-info/METADATA
tikit_en-0.1.220330.dist-info/WHEEL
tikit_en-0.1.220330.dist-info/top_level.txt
tikit_en-0.1.220330.dist-info/RECORD
