Metadata-Version: 2.1
Name: tikit-en
Version: 0.1.220330
Summary: Kit for TI PLATFORM
Home-page: https://cloud.tencent.com/
Author: TI PLATFORM TEAM
Author-email: TI_Platform@tencent.com
License: MIT
Platform: UNKNOWN
Requires-Dist: six (==1.16.0)
Requires-Dist: docopt (==0.6.2)
Requires-Dist: requests (==2.26.0)
Requires-Dist: future (==0.18.2)
Requires-Dist: sasl (==0.3.1)
Requires-Dist: crcmod (==1.7)
Requires-Dist: thrift (==0.15.0)
Requires-Dist: PyHive[hive] (==0.6.4)
Requires-Dist: python-dateutil (==2.8.2)
Requires-Dist: certifi (==2021.10.8)
Requires-Dist: urllib3 (==1.26.7)
Requires-Dist: wcwidth (==0.2.5)
Requires-Dist: pure-sasl (==0.6.2)
Requires-Dist: idna (==3.3)
Requires-Dist: dicttoxml (==1.7.4)
Requires-Dist: prettytable (==2.5.0)
Requires-Dist: hdfs (==2.6.0)
Requires-Dist: cos-python-sdk-v5 (==1.9.14)
Requires-Dist: thrift-sasl (>=0.1.0)
